chaser/__init__.py
chaser/client.py
chaser/connection.py
chaser/const.py
chaser/exceptions.py
chaser/mapping.py
chaser-0.1.dist-info/METADATA
chaser-0.1.dist-info/RECORD
chaser-0.1.dist-info/WHEEL
chaser-0.1.dist-info/top_level.txt
