Metadata-Version: 2.1
Name: chaser
Version: 0.1
Summary: UNKNOWN
Home-page: https://github.com/tokibito/python-chaser
Author: Shinya Okano
Author-email: tokibito@gmail.com
License: UNKNOWN
Platform: UNKNOWN
Classifier: Development Status :: 5 - Production/Stable
Classifier: Programming Language :: Python :: 3.6
Classifier: License :: OSI Approved :: MIT License
Provides-Extra: dev
Requires-Dist: flake8; extra == 'dev'
Requires-Dist: pytest; extra == 'dev'
Requires-Dist: wheel; extra == 'dev'
